<?xml version="1.0" encoding="utf-8"?>
<odoo>
    <record id="res_config_settings_view_form" model="ir.ui.view">
        <field name="name">res.config.settings.view.form.inherit.base.setup</field>
        <field name="model">res.config.settings</field>
        <field name="priority" eval="100"/>
        <field name="inherit_id" ref="base.res_config_settings_view_form"/>
        <field name="arch" type="xml">
            <xpath expr="//div[hasclass('settings')]" position="inside">
                <div class="app_settings_block" data-string="Longitud de rif" string="Longitud de RIF" data-key="RIF">
                    <div id="vat">
                        <h2>Longitud de RIF</h2>
                        <div class="row mt16 o_settings_container">
                            <div class="col-12 col-lg-6 o_setting_box">
                                <div class="o_setting_right_pane">
                                    <span class="o_form_label">Logitud de RIF</span>
                                    <div class="text-muted">
                                        Ingresa la longitud general del campo RIF
                                    </div>
                                    <div class="content-group">
                                        <div class="mt16 row">
                                            <label for="vat_id" string="Logitud" class="col-3 col-lg-3 o_light_label"/>
                                            <field name="vat_id" class="oe_inline" required="1"/>
                                        </div>
                                    </div>
                                </div>
                            </div>
                        </div>
                    </div>
                </div>
            </xpath>
        </field>
    </record>
</odoo>
